haxcore/__init__.py
haxcore/assets/.config/core.yml
haxcore/assets/.config/db.yml
haxcore/assets/.config/log.yml
haxcore/assets/.payloads/sqli.txt
haxcore/assets/.payloads/xss.txt
haxcore/assets/.wordlist/wordlist.txt
haxcore/attacks/__init__.py
haxcore/attacks/attack.py
haxcore/attacks/attack_manager.py
haxcore/attacks/sqli.py
haxcore/attacks/xss.py
haxcore/crack/__init__.py
haxcore/crack/brute_force.py
haxcore/crack/crack_base.py
haxcore/crack/crack_pass_manager.py
haxcore/crack/password_rule.py
haxcore/crack/rainbow.py
haxcore/crack/wordlist_rules.py
haxcore/db/__init__.py
haxcore/db/base.py
haxcore/db/commands.py
haxcore/db/tbl_attack.py
haxcore/db/tbl_setting.py
haxcore/enums.py
haxcore/exception/__init__.py
haxcore/exception/application.py
haxcore/exception/connection.py
haxcore/exception/database.py
haxcore/utilities/__init__.py
haxcore/utilities/attack.py
haxcore/utilities/config.py
haxcore/utilities/log.py
haxcore/utilities/wordlist.py
haxcore-0.0.17.dist-info/LICENSE
haxcore-0.0.17.dist-info/METADATA
haxcore-0.0.17.dist-info/WHEEL
haxcore-0.0.17.dist-info/RECORD
