Metadata-Version: 2.1
Name: haxcore
Version: 0.0.17
Summary: HaX core package
Home-page: https://haxsec.com
License: GNU General Public License v3 (GPLv3)
Keywords: security,cloud,ai,hacking,cybersecurity,hacker,hacking-tool,security-automation,cloudsecurity
Author: Tarek Mulla
Author-email: tarek@mulla.au
Requires-Python: >=3.11,<4.0
Classifier: License :: Other/Proprietary License
Classifier: Programming Language :: Python :: 3
Classifier: Programming Language :: Python :: 3.11
Classifier: Programming Language :: Python :: 3.12
Requires-Dist: bcrypt (>=4.1.1,<5.0.0)
Requires-Dist: colorama (>=0.4.6,<0.5.0)
Requires-Dist: flake8 (>=6.1.0,<7.0.0)
Requires-Dist: isort (>=5.13.0,<6.0.0)
Requires-Dist: mypy (>=1.7.1,<2.0.0)
Requires-Dist: pandas (>=2.1.4,<3.0.0)
Requires-Dist: pylint (>=3.0.2,<4.0.0)
Requires-Dist: pytest (>=7.1.3,<8.0.0)
Requires-Dist: pytest-cov (>=4.1.0,<5.0.0)
Requires-Dist: pytest-mock (>=3.11.1,<4.0.0)
Requires-Dist: pyyaml (>=6.0.1,<7.0.0)
Requires-Dist: requests (>=2.31.0,<3.0.0)
Requires-Dist: toml (>=0.10.2,<0.11.0)
Project-URL: Repository, https://github.com/tarekmulla/hax-core
